LICENSE
MANIFEST.in
README.md
setup.cfg
setup.py
tir/__init__.py
tir/main.py
tir/version.py
tir/technologies/apw_internal.py
tir/technologies/poui_internal.py
tir/technologies/webapp_internal.py
tir/technologies/core/base.py
tir/technologies/core/base_database.py
tir/technologies/core/config.py
tir/technologies/core/enumerations.py
tir/technologies/core/language.py
tir/technologies/core/log.py
tir/technologies/core/logging_config.py
tir/technologies/core/numexec.py
tir/technologies/core/psutil_info.py
tir/technologies/core/data/sx3.csv
tir/technologies/core/drivers/linux64/geckodriver
tir/technologies/core/drivers/windows/chromedriver.exe
tir/technologies/core/drivers/windows/geckodriver.exe
tir/technologies/core/drivers/windows/electron/chromedriver.exe
tir/technologies/core/third_party/screen_size.py
tir/technologies/core/third_party/xpath_soup.py
tir_framework.egg-info/PKG-INFO
tir_framework.egg-info/SOURCES.txt
tir_framework.egg-info/dependency_links.txt
tir_framework.egg-info/requires.txt
tir_framework.egg-info/top_level.txt