Metadata-Version: 2.4
Name: tir_framework
Version: 2.0.0
Summary: Test Interface Robot
Home-page: https://github.com/totvs/tir
Download-URL: https://github.com/totvs/tir
Author: tir_engpro
License: MIT
Project-URL: Script Samples, https://github.com/totvs/tir-script-samples
Keywords: test automation selenium tir totvs protheus framework
Classifier: Environment :: Web Environment
Classifier: Development Status :: 5 - Production/Stable
Classifier: Intended Audience :: Developers
Classifier: Programming Language :: Python :: 3 :: Only
Classifier: Topic :: Documentation :: Sphinx
Classifier: Topic :: Software Development
Classifier: Topic :: Software Development :: Libraries :: Python Modules
Classifier: Topic :: Software Development :: Quality Assurance
Classifier: Topic :: Software Development :: Testing
Requires-Python: ==3.12.*
License-File: LICENSE
Requires-Dist: beautifulsoup4==4.12.3
Requires-Dist: numpy==1.26.4
Requires-Dist: pandas==2.2.1
Requires-Dist: python-dateutil==2.9.0.post0
Requires-Dist: pytz==2024.1
Requires-Dist: selenium==4.19.0
Requires-Dist: six==1.16.0
Requires-Dist: enum34==1.1.10
Requires-Dist: requests==2.31.0
Requires-Dist: pyodbc==5.1.0
Requires-Dist: psutil==5.9.8
Requires-Dist: lxml==5.1.0
Requires-Dist: opencv-python==4.9.0.80
Requires-Dist: webdriver-manager==4.0.2
Dynamic: author
Dynamic: classifier
Dynamic: description
Dynamic: description-content-type
Dynamic: download-url
Dynamic: home-page
Dynamic: keywords
Dynamic: license
Dynamic: license-file
Dynamic: project-url
Dynamic: requires-dist
Dynamic: requires-python
Dynamic: summary
